cpg_flow/__init__.py
cpg_flow/defaults.toml
cpg_flow/filetypes.py
cpg_flow/inputs.py
cpg_flow/metamist.py
cpg_flow/resources.py
cpg_flow/stage.py
cpg_flow/status.py
cpg_flow/utils.py
cpg_flow/workflow.py
cpg_flow/show_workflow/graph.py
cpg_flow/targets/__init__.py
cpg_flow/targets/cohort.py
cpg_flow/targets/dataset.py
cpg_flow/targets/helpers.py
cpg_flow/targets/multicohort.py
cpg_flow/targets/pedigree_info.py
cpg_flow/targets/sequencing_group.py
cpg_flow/targets/target.py
cpg_flow/targets/types.py
cpg_flow-1.3.0.dist-info/licenses/LICENSE
cpg_flow-1.3.0.dist-info/METADATA
cpg_flow-1.3.0.dist-info/WHEEL
cpg_flow-1.3.0.dist-info/top_level.txt
cpg_flow-1.3.0.dist-info/RECORD
