Metadata-Version: 2.4
Name: cpg-flow
Version: 1.3.0
Summary: CPG Flow API for Hail Batch
Project-URL: Repository, https://github.com/populationgenomics/cpg-flow
Keywords: hail,flow,api,bioinformatics,genomics
Classifier: Development Status :: 3 - Alpha
Classifier: Environment :: Console
Classifier: Intended Audience :: Developers
Classifier: Intended Audience :: Science/Research
Classifier: Topic :: Scientific/Engineering
Classifier: Topic :: Scientific/Engineering :: Bio-Informatics
Classifier: Natural Language :: English
Classifier: Operating System :: MacOS :: MacOS X
Classifier: Operating System :: POSIX
Classifier: Operating System :: Unix
Classifier: Programming Language :: Python :: 3
Classifier: Programming Language :: Python :: 3.10
Requires-Python: <3.12,>=3.10
License-File: LICENSE
Requires-Dist: cpg-utils>=5.4.2
Requires-Dist: hail==0.2.137
Requires-Dist: grpcio>=1.53.0
Requires-Dist: grpcio-status<1.50,>=1.48
Requires-Dist: loguru>0.7.0
Requires-Dist: metamist>=7.13.0
Requires-Dist: networkx>=3.4.2
Requires-Dist: pyyaml>=6.0.2
Requires-Dist: plotly>=5.24.1
Requires-Dist: ipywidgets>=8.1.5
Requires-Dist: pre-commit>=4.0.1
Requires-Dist: tornado>=6.5
Dynamic: license-file
